aws_utility_library_savicppapp/__init__.py
aws_utility_library_savicppapp/dynamodb.py
aws_utility_library_savicppapp/lambda_utility.py
aws_utility_library_savicppapp/s3.py
aws_utility_library_savicppapp/sqs_sns.py
aws_utility_library_savicppapp-1.0.0.dist-info/LICENSE
aws_utility_library_savicppapp-1.0.0.dist-info/METADATA
aws_utility_library_savicppapp-1.0.0.dist-info/WHEEL
aws_utility_library_savicppapp-1.0.0.dist-info/top_level.txt
aws_utility_library_savicppapp-1.0.0.dist-info/RECORD
